{
  "id": "878937428",
  "gender": 1,
  "tutor": "878937428",
  "subjects": [
    "Algebra"
  ],
  "tutoringExperience": 3,
  "sessions": 1,
  "students": 1,
  "trackingHistory": [
    {
      "sessionId": "e3a9f37d-8944-472c-9df6-48403e95e941",
      "subject": "Algebra",
      "date": "2023-10-24"
    }
  ],
  "scoreTrend": {
    "instructionalDelivery": [
      6
    ],
    "techToolUsage": [
      10
    ],
    "feedbackQuality": [
      4
    ],
    "socialEmotionalTeaching": [
      4
    ],
    "time": [
      0
    ]
  }
}